convnextpl/__init__.py
convnextpl/data/__init__.py
convnextpl/data/imagedataset.py
convnextpl/models/__init__.py
convnextpl/models/blocks.py
convnextpl/models/convnext.py
convnextpl/models/convnext_isotropic.py
convnextpl-0.0.1.dist-info/LICENSE
convnextpl-0.0.1.dist-info/METADATA
convnextpl-0.0.1.dist-info/WHEEL
convnextpl-0.0.1.dist-info/top_level.txt
convnextpl-0.0.1.dist-info/RECORD
